PyMatterSim/__init__.py
PyMatterSim/_acc/__init__.py
PyMatterSim/_acc/acc.cpython-311-darwin.so
PyMatterSim/dynamic/__init__.py
PyMatterSim/dynamic/dynamics.py
PyMatterSim/dynamic/time_corr.py
PyMatterSim/neighbors/__init__.py
PyMatterSim/neighbors/calculate_neighbors.py
PyMatterSim/neighbors/freud_neighbors.py
PyMatterSim/neighbors/read_neighbors.py
PyMatterSim/neighbors/voropp_neighbors.py
PyMatterSim/reader/__init__.py
PyMatterSim/reader/dump_reader.py
PyMatterSim/reader/gsd_reader_helper.py
PyMatterSim/reader/lammps_reader_helper.py
PyMatterSim/reader/reader_utils.py
PyMatterSim/reader/simulation_log.py
PyMatterSim/static/__init__.py
PyMatterSim/static/boo.py
PyMatterSim/static/geometric.py
PyMatterSim/static/gr.py
PyMatterSim/static/hessians.py
PyMatterSim/static/nematic.py
PyMatterSim/static/pairentropy.py
PyMatterSim/static/shape.py
PyMatterSim/static/sq.py
PyMatterSim/static/topodefect.py
PyMatterSim/static/vector.py
PyMatterSim/static/xtalplane.py
PyMatterSim/utils/__init__.py
PyMatterSim/utils/coarse_graining.py
PyMatterSim/utils/fft.py
PyMatterSim/utils/fitting.py
PyMatterSim/utils/funcs.py
PyMatterSim/utils/geometry.py
PyMatterSim/utils/logging.py
PyMatterSim/utils/pbc.py
PyMatterSim/utils/plots.py
PyMatterSim/utils/spherical_harmonics.py
PyMatterSim/utils/wavevector.py
PyMatterSim/writer/__init__.py
PyMatterSim/writer/lammps_writer.py
tests/__init__.py
tests/dynamics/__init__.py
tests/dynamics/dynamic_test.py
tests/dynamics/time_corr_test.py
tests/neighbors/__init__.py
tests/neighbors/calculate_neighbors_test.py
tests/neighbors/freud_neighbors_test.py
tests/neighbors/read_neighbors_test.py
tests/neighbors/voropp_neighbors_test.py
tests/reader/__init__.py
tests/reader/dump_reader_test.py
tests/reader/gsd_reader_helper_test.py
tests/reader/lammps_reader_helper_test.py
tests/reader/log_reader_test.py
tests/static/__init__.py
tests/static/boo_test.py
tests/static/geometric_test.py
tests/static/gr_test.py
tests/static/hessian_test.py
PyMatterSim-0.2.4.dist-info/LICENSE
PyMatterSim-0.2.4.dist-info/METADATA
PyMatterSim-0.2.4.dist-info/WHEEL
PyMatterSim-0.2.4.dist-info/top_level.txt
PyMatterSim-0.2.4.dist-info/RECORD
