Metadata-Version: 2.1
Name: PyMatterSim
Version: 0.2.4
Summary: A python data analysis library for computer simulations
Home-page: https://gitee.com/yuanchaohu/pymattersim
Author: Yuan-Chao Hu
Author-email: ychu0213@gmail.com
Classifier: Programming Language :: Python :: 3
Classifier: License :: OSI Approved :: MIT License
Classifier: Operating System :: OS Independent
Requires-Python: >=3.8
License-File: LICENSE
Requires-Dist: numpy
Requires-Dist: pandas
Requires-Dist: freud-analysis
Requires-Dist: scipy
Requires-Dist: sympy
Requires-Dist: ovito ==3.12.4
Requires-Dist: matplotlib
